mellow/Classifiers.py
mellow/Regressor.py
mellow/__init__.py
mellow/classifiers.py
mellow/main.py
mellow/ml.py
mellow/regressor.py
mellow/utility.py
mellow-0.0.0.9.dist-info/LICENSE
mellow-0.0.0.9.dist-info/METADATA
mellow-0.0.0.9.dist-info/WHEEL
mellow-0.0.0.9.dist-info/entry_points.txt
mellow-0.0.0.9.dist-info/top_level.txt
mellow-0.0.0.9.dist-info/RECORD
