Metadata-Version: 2.1
Name: mellow
Version: 0.0.0.9
Summary: machine learning algorithms
Home-page: https://github.com/macabdul9/mellow
Author: Abdul Waheed
Author-email: abdulwaheed1513@gmail.com
License: License :: OSI Approved :: MIT License
Keywords: machine-learning
Platform: UNKNOWN
Classifier: Development Status :: 3 - Alpha
Classifier: Programming Language :: Python
Classifier: Programming Language :: Python :: 3
Classifier: Operating System :: OS Independent
Requires-Python: >=2.7
Requires-Dist: beautifulsoup4
Requires-Dist: pandas
Requires-Dist: numpy
Requires-Dist: matplotlib
Requires-Dist: opencv-python
